ndsl/__init__.py
ndsl/example.py
ndsl/architecture/__init__.py
ndsl/architecture/attention.py
ndsl/architecture/feature_selection.py
ndsl/module/__init__.py
ndsl/module/aggregator.py
ndsl/module/encoder.py
ndsl/module/preprocessor.py
ndsl_attn_fs_archs-0.0.7.dist-info/LICENSE
ndsl_attn_fs_archs-0.0.7.dist-info/METADATA
ndsl_attn_fs_archs-0.0.7.dist-info/WHEEL
ndsl_attn_fs_archs-0.0.7.dist-info/top_level.txt
ndsl_attn_fs_archs-0.0.7.dist-info/RECORD
