Metadata-Version: 2.1
Name: ndsl-attn-fs-archs
Version: 0.0.7
Summary: Architecture described in paper: Transformers for high-dimensional tabular data
Home-page: https://github.com/cobu93/attn-fs-archs
Author: Under ML
Author-email: urielcoro@gmail.com
Classifier: Topic :: Scientific/Engineering :: Artificial Intelligence
Classifier: Development Status :: 4 - Beta
Classifier: License :: Other/Proprietary License
Classifier: Programming Language :: Python :: 3
License-File: LICENSE
